{
  "$schema": "https://biomejs.dev/schemas/1.9.4/schema.json",
  "organizeImports": {
    "enabled": true
  },
  "linter": {
    "enabled": true,
    "rules": {
      "recommended": true,
      "style": {
        "noNonNullAssertion": "off",
        "useImportType": "error"
      },
      "suspicious": {
        "noExplicitAny": "warn",
        "noArrayIndexKey": "warn"
      },
      "correctness": {
        "useExhaustiveDependencies": "warn"
      },
      "complexity": {
        "noForEach": "off"
      }
    }
  },
  "formatter": {
    "enabled": true,
    "formatWithErrors": false,
    "indentStyle": "space",
    "indentWidth": 2,
    "lineEnding": "lf",
    "lineWidth": 100,
    "attributePosition": "auto"
  },
  "javascript": {
    "formatter": {
      "jsxQuoteStyle": "double",
      "quoteProperties": "asNeeded",
      "trailingCommas": "es5",
      "semicolons": "always",
      "arrowParentheses": "always",
      "bracketSpacing": true,
      "bracketSameLine": false,
      "quoteStyle": "single",
      "attributePosition": "auto"
    }
  },
  "json": {
    "formatter": {
      "enabled": true
    }
  },
  "files": {
    "include": ["**/*.ts", "**/*.tsx", "**/*.json"],
    "ignore": [
      "node_modules/**",
      "dist/**",
      ".next/**",
      ".remix/**",
      "coverage/**",
      "storybook-static/**"
    ]
  }
}
